habit_tracking_app/__init__.py
habit_tracking_app/main.py
habit_tracking_app/test_all.py
habit_tracking_app/database/predefined_habits.sql
habit_tracking_app/database/table.sql
habit_tracking_app/frames/__init__.py
habit_tracking_app/frames/add_new_habit_page.py
habit_tracking_app/frames/analytics_page.py
habit_tracking_app/frames/delete_habit_page.py
habit_tracking_app/frames/edit_habit_page.py
habit_tracking_app/frames/exit_page.py
habit_tracking_app/frames/habits_page.py
habit_tracking_app/frames/home_page.py
habit_tracking_app/frames/mark_as_completed_page.py
habit_tracking_app/frames/navigation_menu.py
habit_tracking_app/frames/reset_data_page.py
habit_tracking_app/frames/settings_page.py
habit_tracking_app/frames/functions/__init__.py
habit_tracking_app/frames/functions/config.py
habit_tracking_app/frames/functions/database.py
habit_tracking_app/frames/functions/display_data_frame.py
habit_tracking_app/frames/functions/habit.py
habit_tracking_app/frames/functions/icons.py
habit_tracking_app/icons/analytics_dark_mode.png
habit_tracking_app/icons/analytics_light_mode.png
habit_tracking_app/icons/exit_dark_mode.png
habit_tracking_app/icons/exit_light_mode.png
habit_tracking_app/icons/habits_dark_mode.png
habit_tracking_app/icons/habits_light_mode.png
habit_tracking_app/icons/home_dark_mode.png
habit_tracking_app/icons/home_light_mode.png
habit_tracking_app/icons/settings_dark_mode.png
habit_tracking_app/icons/settings_light_mode.png
habit_tracking_app/tests/__init__.py
habit_tracking_app/tests/test_add_new_habit_page.py
habit_tracking_app/tests/test_analytics_page.py
habit_tracking_app/tests/test_config.py
habit_tracking_app/tests/test_database.py
habit_tracking_app/tests/test_delete_habit_page.py
habit_tracking_app/tests/test_display_data_frame.py
habit_tracking_app/tests/test_edit_habit_page.py
habit_tracking_app/tests/test_exit_page.py
habit_tracking_app/tests/test_habit.py
habit_tracking_app/tests/test_habits_page.py
habit_tracking_app-0.0.4.dist-info/LICENSE
habit_tracking_app-0.0.4.dist-info/METADATA
habit_tracking_app-0.0.4.dist-info/WHEEL
habit_tracking_app-0.0.4.dist-info/entry_points.txt
habit_tracking_app-0.0.4.dist-info/top_level.txt
habit_tracking_app-0.0.4.dist-info/RECORD
