Metadata-Version: 2.1
Name: habit-tracking-app
Version: 0.0.4
Summary: Habit tracking application
Home-page: https://github.com/fufuthesloth/habit-tracking-app/
Author: Krzysztof Szczypkowski
Author-email: krzysztof.szczypkowski@o2.pl
License: Unlicense
Keywords: habit tracking,gui,executable
Classifier: License :: OSI Approved :: The Unlicense (Unlicense)
Classifier: Programming Language :: Python
Classifier: Programming Language :: Python :: 3
Classifier: Programming Language :: Python :: 3.10
Classifier: Programming Language :: Python :: 3.11
Classifier: Operating System :: Microsoft :: Windows
Requires-Python: >=3.10
License-File: LICENSE
Requires-Dist: customtkinter (>=5.1.2)
Requires-Dist: tkcalendar (>=1.6.1)
Requires-Dist: Pillow (>=9.4.0)
